kpi_formula/__init__.py
kpi_formula/advanced/__init__.py
kpi_formula/advanced/data_processor.py
kpi_formula/advanced/data_validator.py
kpi_formula/advanced/kpi_calculator.py
kpi_formula/advanced/time_series.py
kpi_formula/core/__init__.py
kpi_formula/core/data_manager.py
kpi_formula/core/join_manager.py
kpi_formula/core/models.py
kpi_formula/core/operations.py
kpi_formula/utils/__init__.py
kpi_formula_t5-0.2.5.dist-info/LICENSE
kpi_formula_t5-0.2.5.dist-info/METADATA
kpi_formula_t5-0.2.5.dist-info/WHEEL
kpi_formula_t5-0.2.5.dist-info/top_level.txt
kpi_formula_t5-0.2.5.dist-info/RECORD
