Metadata-Version: 2.1
Name: kpi-formula-t5
Version: 0.2.5
Summary: A KPI calculation tool
Home-page: https://github.com/leoren1314/kpi-formula
Author: 4485-t5
Author-email: leoren1314@gmail.com
Project-URL: Bug Reports, https://github.com/Meliodas417/AG-T5
Project-URL: Source, https://github.com/Meliodas417/AG-T5
Classifier: Development Status :: 3 - Alpha
Classifier: Intended Audience :: Developers
Classifier: License :: OSI Approved :: MIT License
Classifier: Operating System :: OS Independent
Classifier: Programming Language :: Python :: 3
Classifier: Programming Language :: Python :: 3.7
Classifier: Programming Language :: Python :: 3.8
Classifier: Programming Language :: Python :: 3.9
Requires-Python: >=3.7
License-File: LICENSE
Requires-Dist: pandas>=1.0.0
Requires-Dist: numpy>=1.18.0
Requires-Dist: openpyxl>=3.0.0
Requires-Dist: sqlalchemy>=1.4.0
Requires-Dist: pymysql>=1.0.0
Requires-Dist: psycopg2-binary>=2.9.0
Requires-Dist: pyarrow>=5.0.0
Requires-Dist: statistics
Requires-Dist: flask>=2.0.0
Provides-Extra: dev
Requires-Dist: pytest>=6.0.0; extra == "dev"
Requires-Dist: pytest-cov>=2.0.0; extra == "dev"
Requires-Dist: black>=21.0.0; extra == "dev"
Provides-Extra: mysql
Requires-Dist: pymysql>=1.0.0; extra == "mysql"
Provides-Extra: postgresql
Requires-Dist: psycopg2-binary>=2.9.0; extra == "postgresql"
